{
  "originalFilePath": "",
  "minionTaskId": "",
  "pluginVersion": "",
  "vsCodeVersion": "",
  "date": "",
  "score": "",
  "testResults": [
    { "score": "100%", "date": "2023-08-31_18-10-46" },
    {
      "score": "100%",
      "date": "2023-09-01_11-32-24",
      "testQueueName": "Old CodeChange strategy test",
      "iterations": 10
    },
    {
      "score": "100%",
      "date": "2023-09-01_22-28-12",
      "testQueueName": "NEW CodeChange (with step evolve) strategy test",
      "iterations": 10
    }
  ]
}
